xql/__init__.py
xql/nosql.py
xql/sql.py
xql-0.1.0.dist-info/licenses/LICENSE
xql-0.1.0.dist-info/METADATA
xql-0.1.0.dist-info/WHEEL
xql-0.1.0.dist-info/entry_points.txt
xql-0.1.0.dist-info/top_level.txt
xql-0.1.0.dist-info/RECORD
